<annotation>
  <folder></folder>
  <filename>gesture/train/image/1285.jpg</filename>
  <source>
    <database>Unknown</database>
    <annotation>Unknown</annotation>
    <image>Unknown</image>
  </source>
  <size>
    <width>200</width>
    <height>300</height>
    <depth></depth>
  </size>
  <segmented>0</segmented>
  <object>
    <name>Insult</name>
    <truncated>0</truncated>
    <occluded>0</occluded>
    <difficult>0</difficult>
    <bndbox>
      <xmin>34.51</xmin>
      <ymin>12.39</ymin>
      <xmax>162.39</xmax>
      <ymax>234.51</ymax>
    </bndbox>
  </object>
</annotation>
