<annotation>
  <folder></folder>
  <filename>gesture/train/image/2609.jpg</filename>
  <source>
    <database>Unknown</database>
    <annotation>Unknown</annotation>
    <image>Unknown</image>
  </source>
  <size>
    <width>960</width>
    <height>1280</height>
    <depth></depth>
  </size>
  <segmented>0</segmented>
  <object>
    <name>Two</name>
    <truncated>0</truncated>
    <occluded>0</occluded>
    <difficult>0</difficult>
    <bndbox>
      <xmin>367.58</xmin>
      <ymin>338.8</ymin>
      <xmax>857.7</xmax>
      <ymax>1263.58</ymax>
    </bndbox>
  </object>
</annotation>
