<annotation>
  <folder></folder>
  <filename>gesture/train/image/2653.jpg</filename>
  <source>
    <database>Unknown</database>
    <annotation>Unknown</annotation>
    <image>Unknown</image>
  </source>
  <size>
    <width>3024</width>
    <height>4032</height>
    <depth></depth>
  </size>
  <segmented>0</segmented>
  <object>
    <name>Two</name>
    <truncated>0</truncated>
    <occluded>0</occluded>
    <difficult>0</difficult>
    <bndbox>
      <xmin>598.56</xmin>
      <ymin>1159.26</ymin>
      <xmax>2110.56</xmax>
      <ymax>3521.76</ymax>
    </bndbox>
  </object>
</annotation>
