<annotation>
  <folder></folder>
  <filename>gesture/train/image/3461.jpg</filename>
  <source>
    <database>Unknown</database>
    <annotation>Unknown</annotation>
    <image>Unknown</image>
  </source>
  <size>
    <width>800</width>
    <height>600</height>
    <depth></depth>
  </size>
  <segmented>0</segmented>
  <object>
    <name>Insult</name>
    <truncated>0</truncated>
    <occluded>0</occluded>
    <difficult>0</difficult>
    <bndbox>
      <xmin>317.53</xmin>
      <ymin>260.62</ymin>
      <xmax>484.41</xmax>
      <ymax>582.19</ymax>
    </bndbox>
  </object>
</annotation>
