<annotation>
  <folder></folder>
  <filename>gesture/train/image/3503.jpg</filename>
  <source>
    <database>Unknown</database>
    <annotation>Unknown</annotation>
    <image>Unknown</image>
  </source>
  <size>
    <width>800</width>
    <height>600</height>
    <depth></depth>
  </size>
  <segmented>0</segmented>
  <object>
    <name>Nine</name>
    <truncated>0</truncated>
    <occluded>0</occluded>
    <difficult>0</difficult>
    <bndbox>
      <xmin>304.41</xmin>
      <ymin>159.38</ymin>
      <xmax>475.03</xmax>
      <ymax>511.88</ymax>
    </bndbox>
  </object>
</annotation>
