<annotation>
  <folder></folder>
  <filename>gesture/train/image/3638.jpg</filename>
  <source>
    <database>Unknown</database>
    <annotation>Unknown</annotation>
    <image>Unknown</image>
  </source>
  <size>
    <width>800</width>
    <height>600</height>
    <depth></depth>
  </size>
  <segmented>0</segmented>
  <object>
    <name>Eight</name>
    <truncated>0</truncated>
    <occluded>0</occluded>
    <difficult>0</difficult>
    <bndbox>
      <xmin>332.62</xmin>
      <ymin>97.87</ymin>
      <xmax>729.08</xmax>
      <ymax>470.21</ymax>
    </bndbox>
  </object>
</annotation>
