<annotation>
  <folder></folder>
  <filename>gesture/train/image/3801.jpg</filename>
  <source>
    <database>Unknown</database>
    <annotation>Unknown</annotation>
    <image>Unknown</image>
  </source>
  <size>
    <width>1280</width>
    <height>720</height>
    <depth></depth>
  </size>
  <segmented>0</segmented>
  <object>
    <name>Three</name>
    <truncated>0</truncated>
    <occluded>0</occluded>
    <difficult>0</difficult>
    <bndbox>
      <xmin>362.92</xmin>
      <ymin>80.49</ymin>
      <xmax>824.72</xmax>
      <ymax>704.15</ymax>
    </bndbox>
  </object>
</annotation>
