<annotation>
  <folder></folder>
  <filename>gesture/train/image/437.jpg</filename>
  <source>
    <database>Unknown</database>
    <annotation>Unknown</annotation>
    <image>Unknown</image>
  </source>
  <size>
    <width>2976</width>
    <height>3968</height>
    <depth></depth>
  </size>
  <segmented>0</segmented>
  <object>
    <name>Four</name>
    <truncated>0</truncated>
    <occluded>0</occluded>
    <difficult>0</difficult>
    <bndbox>
      <xmin>93.3</xmin>
      <ymin>359.9</ymin>
      <xmax>2455.5</xmax>
      <ymax>3931.1</ymax>
    </bndbox>
  </object>
</annotation>
