<annotation>
  <folder></folder>
  <filename>gesture/train/image/916.jpg</filename>
  <source>
    <database>Unknown</database>
    <annotation>Unknown</annotation>
    <image>Unknown</image>
  </source>
  <size>
    <width>607</width>
    <height>900</height>
    <depth></depth>
  </size>
  <segmented>0</segmented>
  <object>
    <name>Heart_single</name>
    <truncated>0</truncated>
    <occluded>0</occluded>
    <difficult>0</difficult>
    <bndbox>
      <xmin>20.67</xmin>
      <ymin>316.4</ymin>
      <xmax>442.5</xmax>
      <ymax>858.11</ymax>
    </bndbox>
  </object>
</annotation>
