<annotation>
  <folder></folder>
  <filename>gesture/train/image/937.jpg</filename>
  <source>
    <database>Unknown</database>
    <annotation>Unknown</annotation>
    <image>Unknown</image>
  </source>
  <size>
    <width>194</width>
    <height>264</height>
    <depth></depth>
  </size>
  <segmented>0</segmented>
  <object>
    <name>Heart_single</name>
    <truncated>0</truncated>
    <occluded>0</occluded>
    <difficult>0</difficult>
    <bndbox>
      <xmin>27.7</xmin>
      <ymin>7.74</ymin>
      <xmax>182.76</xmax>
      <ymax>216.9</ymax>
    </bndbox>
  </object>
</annotation>
